[
  {
    "h1_id" : "1",
    "page": "index",
    "h1" : "Welcome"
  }, {
    "h1_id" : "2",
    "page": "blog",
    "h1" : "My Blog"
  },{
    "h1_id" : "3",
    "page": "about",
    "h1" : "This is the About Page"
  }, {
    "h1_id" : "4",
    "page": "batman",
    "h1" : "Batman TV Shows"
  }, {
    "h1_id" : "5",
    "page": "contact",
    "h1" : "Contacts"
  },
  {
    "h1_id" : "6",
    "page": "test",
    "h1" : "Course shows"
  },
  {
    "h1_id" : "7",
    "page": "log&Sign",
    "h1" : "log&Sign"
  },
  {
    "h1_id" : "8",
    "page": "404",
    "h1" : "404 Not Found"
  }
]
